routinepy/consts.py
routinepy/cli/__init__.py
routinepy/cli/__main__.py
routinepy/cli/dataclasses.py
routinepy/cli/parsers.py
routinepy/cli/utils.py
routinepy/lib/__init__.py
routinepy/lib/exceptions.py
routinepy/lib/models.py
routinepy/lib/api/client.py
routinepy/lib/api/enums.py
routinepy/lib/scraper/client.py
routinepy/lib/scraper/models.py
routinepy/lib/scraper/scraper_utils.py
routinepy/lib/scraper/parsers/html/__init__.py
routinepy/lib/scraper/parsers/html/class_routine.py
routinepy/lib/scraper/parsers/html/routine_page.py
routinepy/lib/scraper/parsers/pdf/__init__.py
routinepy/lib/scraper/parsers/pdf/exam_routine.py
routinepy/lib/scraper/parsers/pdf/exam_routine_006.py
routinepy/lib/scraper/transformers/__init__.py
routinepy/lib/scraper/transformers/class_routine.py
routinepy/lib/scraper/transformers/exam_routine.py
routinepy/lib/scraper/transformers/exam_routine_006.py
routinepy/lib/utils/dt_utils.py
routinepy/lib/utils/grouping.py
routinepy/lib/utils/http.py
routinepy/lib/utils/table_generator.py
bubt_routinepy-1.0.0.dist-info/METADATA
bubt_routinepy-1.0.0.dist-info/WHEEL
bubt_routinepy-1.0.0.dist-info/entry_points.txt
bubt_routinepy-1.0.0.dist-info/licenses/LICENSE
bubt_routinepy-1.0.0.dist-info/RECORD
