Metadata-Version: 2.4
Name: bubt-routinepy
Version: 1.0.0
Summary: An unofficial Python wrapper of the BUBT Routine API + a robust web scraper and PDF extractor for getting routine data.
Project-URL: Homepage, https://github.com/kurtnettle/bubt-routinepy
Project-URL: Documentation, https://bubt-routinepy.readthedocs.io
Project-URL: Repository, https://github.com/kurtnettle/bubt-routinepy
Author-email: Shaikh Shafeen <shafeen@duck.com>
Maintainer-email: Shaikh Shafeen <shafeen@duck.com>
License-Expression: GPL-3.0-only
License-File: LICENSE
Keywords: api,asyncio,bubt,class,exam,faculty,routine,wrapper
Requires-Python: >=3.11
Requires-Dist: aiohttp-client-cache[sqlite]>=0.13.0
Requires-Dist: aiohttp>=3.12.0
Requires-Dist: beautifulsoup4>=4.13.4
Requires-Dist: loguru>=0.7.3
Requires-Dist: lxml>=5.4.0
Requires-Dist: pdfplumber>=0.11.6
Requires-Dist: prettytable>=3.16.0
Requires-Dist: pydantic>=2.11.5
